spasm/__init__.py
spasm/parsers/StatementLineParser.py
spasm/parsers/StatementLineParserListener.py
spasm/parsers/__init__.py
spasm/parsers/consts.py
spasm/pp/__init__.py
spasm/pp/__main__.py
spasm/pp/_utils.py
spasm/pp/cli.py
spasm/pp/processor.py
spasm/pp/statement_line/__init__.py
spasm/pp/statement_line/model.py
spasm/pp/statement_line/parser.py
spasm/pp/statement_line/renderer.py
spasm/pp/stylesheet/__init__.py
spasm/pp/stylesheet/builtin.py
spasm/pp/stylesheet/loader.py
spasm/pp/stylesheet/validation.py
spasm_by_sporniket-1.1.0.dist-info/METADATA
spasm_by_sporniket-1.1.0.dist-info/WHEEL
spasm_by_sporniket-1.1.0.dist-info/entry_points.txt
spasm_by_sporniket-1.1.0.dist-info/licenses/LICENCE
spasm_by_sporniket-1.1.0.dist-info/RECORD
