Metadata-Version: 2.1
Name: spasm-by-sporniket
Version: 1.1.0
Summary: Sporniket's toolbox for assembly language
Keywords: assembler,pretty printer
Author-Email: Sporniket <sporniket.studio@gmail.com>
License: GPL-3.0-or-later
Project-URL: homepage, https://github.com/sporniket/spasm
Project-URL: repository, https://github.com/sporniket/spasm
Project-URL: bug-tracker, https://github.com/sporniket/spasm/issues
Requires-Python: >=3.9
